LICENSE
MANIFEST.in
README.rst
setup.cfg
setup.py
pytwitterwallv/__init__.py
pytwitterwallv/__main__.py
pytwitterwallv/pytwitterwallv.py
pytwitterwallv.egg-info/PKG-INFO
pytwitterwallv.egg-info/SOURCES.txt
pytwitterwallv.egg-info/dependency_links.txt
pytwitterwallv.egg-info/entry_points.txt
pytwitterwallv.egg-info/not-zip-safe
pytwitterwallv.egg-info/requires.txt
pytwitterwallv.egg-info/top_level.txt
pytwitterwallv/templates/wall.html
tests/test_integration.py
tests/fixtures/tweets.json
tests/fixtures/cassettes/test_integration.test_twitter_client.json
tests/fixtures/cassettes/test_integration.test_web.json