Metadata-Version: 1.1
Name: pytwitterwallv
Version: 0.7
Summary: Console and web simple client for Twitter
Home-page: https://github.com/vknaisl/pytwitterwallv
Author: Vojtech Knaisl
Author-email: vknaisl@gmail.com
License: Public Domain
Keywords: twitter,tweets
Platform: UNKNOWN
Classifier: Programming Language :: Python
Classifier: Programming Language :: Python :: Implementation :: CPython
Classifier: Programming Language :: Python :: 3
Classifier: Programming Language :: Python :: 3.5
Classifier: Topic :: Internet :: WWW/HTTP
Classifier: Topic :: Internet :: WWW/HTTP :: WSGI
Classifier: Topic :: Internet :: WWW/HTTP :: WSGI :: Application
